[
  {"content": "Мы становимся тем, о чём думаем.", "author": "Эрл Найтингейл"},
  {"content": "Счастье — это путь, а не пункт назначения.", "author": "Неизвестен"},
  {"content": "Если можешь мечтать об этом — сможешь и сделать.", "author": "Уолт Дисней"},
  {"content": "Будь изменением, которое хочешь видеть в мире.", "author": "Махатма Ганди"},
  {"content": "Жизнь начинается там, где заканчивается страх.", "author": "Ошо"},
  {"content": "Пока ты не сдаёшься — ты не проиграл.", "author": "Марк Леви"},
  {"content": "Мысли формируют реальность.", "author": "Будда"},
  {"content": "Будущее создаётся сегодня.", "author": "Неизвестен"},
  {"content": "Каждый день — новый шанс.", "author": "Неизвестен"},
  {"content": "Не ошибается тот, кто ничего не делает.", "author": "Теодор Рузвельт"},
  {"content": "Страх — враг роста.", "author": "Неизвестен"},
  {"content": "Сомнения убивают больше мечтаний, чем неудачи.", "author": "Сьюзи Кэссем"},
  {"content": "Начни там, где ты есть.", "author": "Артур Эш"},
  {"content": "Главное — начать.", "author": "Неизвестен"},
  {"content": "Делай, что можешь, с тем, что имеешь.", "author": "Теодор Рузвельт"},
  {"content": "Ты сильнее, чем думаешь.", "author": "Неизвестен"},
  {"content": "Перемены начинаются с решения.", "author": "Неизвестен"},
  {"content": "Привычки формируют судьбу.", "author": "Неизвестен"},
  {"content": "Терпение — ключ к успеху.", "author": "Неизвестен"},
  {"content": "Всему своё время.", "author": "Экклезиаст"},
  {"content": "Мы — то, что делаем регулярно.", "author": "Аристотель"},
  {"content": "Сначала мы создаём привычки, затем привычки создают нас.", "author": "Неизвестен"},
  {"content": "Не сравнивай себя с другими.", "author": "Неизвестен"},
  {"content": "Будь благодарен за то, что имеешь.", "author": "Неизвестен"},
  {"content": "Сложности — это ступени роста.", "author": "Неизвестен"},
  {"content": "Ты — единственный ограничитель.", "author": "Неизвестен"},
  {"content": "Ошибки — это опыт.", "author": "Неизвестен"},
  {"content": "Каждый день — маленькая жизнь.", "author": "Сенека"},
  {"content": "Осознанность — путь к свободе.", "author": "Неизвестен"},
  {"content": "Спокойствие — это суперсила.", "author": "Неизвестен"},
  {"content": "Настоящее — всё, что есть.", "author": "Экхарт Толле"},
  {"content": "В моменте нет проблем.", "author": "Экхарт Толле"},
  {"content": "Делай сегодня то, за что завтра скажешь себе спасибо.", "author": "Неизвестен"},
  {"content": "Лучший день — сегодня.", "author": "Неизвестен"},
  {"content": "Там, где страх, там сила роста.", "author": "Неизвестен"},
  {"content": " discipline = freedom.", "author": "Джоко Уиллинк"},
  {"content": "Знание — сила, а действие — её применение.", "author": "Неизвестен"},
  {"content": "Если устал — научись отдыхать, а не сдаваться.", "author": "Бэнкс"},
  {"content": "Ты можешь больше, чем предполагаешь.", "author": "Неизвестен"},
  {"content": "Секрет успеха — в регулярности.", "author": "Неизвестен"},
  {"content": "Самое трудное — решиться.", "author": "Неизвестен"},
  {"content": "Все победы начинаются в голове.", "author": "Неизвестен"},
  {"content": "Не нужно быть идеальным — нужно быть собой.", "author": "Неизвестен"},
  {"content": "Время всё расставит по местам.", "author": "Неизвестен"},
  {"content": "Вопрос — половина ответа.", "author": "Неизвестен"},
  {"content": "Там, где фокус, там энергия.", "author": "Неизвестен"},
  {"content": "Иногда пустота — это начало.", "author": "Неизвестен"},
  {"content": "Умение ждать — искусство.", "author": "Неизвестен"},
  {"content": "Свобода начинается внутри.", "author": "Неизвестен"}
]
